MANIFEST.in
README.md
setup.py
aosss/__init__.py
aosss/mosaic.py
aosss/report.py
aosss/util.py
aosss.egg-info/PKG-INFO
aosss.egg-info/SOURCES.txt
aosss.egg-info/dependency_links.txt
aosss.egg-info/requires.txt
aosss.egg-info/top_level.txt
aosss/basic/__init__.py
aosss/basic/conversion.py
aosss/basic/maths.py
aosss/basic/misc.py
aosss/blocks/__init__.py
aosss/blocks/basic.py
aosss/blocks/gb.py
aosss/blocks/sb.py
aosss/blocks/slb.py
aosss/blocks/toscalar.py
aosss/data/README.txt
aosss/data/_plot-eso-sky.py
aosss/data/atmos_S_H.fits
aosss/data/atmos_S_J.fits
aosss/data/atmos_S_K.fits
aosss/data/atmos_S_L.fits
aosss/data/atmos_S_M.fits
aosss/data/atmos_S_SZ.fits
aosss/data/eso-sky.fits
aosss/data/telluric-5000-10000.fits
aosss/filetypes/__init__.py
aosss/filetypes/filefullcube.py
aosss/filetypes/filepar.py
aosss/filetypes/filesparsecube.py
aosss/filetypes/filesplist.py
aosss/filetypes/fullcube.py
aosss/filetypes/sparsecube.py
aosss/filetypes/spcollection.py
aosss/filetypes/splist.py
aosss/gui/__a_WChooseSpectrum.py
aosss/gui/__init__.py
aosss/gui/a_WFileSparseCube.py
aosss/gui/a_WFileSpectrumList.py
aosss/gui/a_WSparseCube.py
aosss/gui/a_WSpectrumCollectionBase.py
aosss/gui/a_WSpectrumList.py
aosss/gui/a_XFileSparseCube.py
aosss/gui/a_XFileSpectrumList.py
aosss/gui/a_XGroupSpectra.py
aosss/gui/a_XHelpDialog.py
aosss/gui/a_XPlotXY.py
aosss/gui/a_XPlotXYZ.py
aosss/gui/a_XScaleSpectrum.py
aosss/gui/a_XToScalar.py
aosss/gui/a_XUseSpectrumBlock.py
aosss/physics/__init__.py
aosss/physics/photometry.py
aosss/physics/rainbow.py
aosss/physics/sp2rgb.py
aosss/scripts/create-simulation-reports.py
aosss/scripts/create-spectrum-lists.py
aosss/scripts/cubeed.py
aosss/scripts/get-compass.py
aosss/scripts/list-mosaic-modes.py
aosss/scripts/organize-directory.py
aosss/scripts/splisted.py
aosss/scripts/wavelength-chart.py
aosss/vis/__init__.py
aosss/vis/draw_cube.py
aosss/vis/vismisc.py