Metadata-Version: 1.0
Name: aosss
Version: 17.12.21.0
Summary: Adaptive Optics Systems Simulation Support
Home-page: https://github.com/trevisanj/aosss
Author: Julio Trevisan
Author-email: juliotrevisan@gmail.com
License: GNU GPLv3
Keywords: astronomy,instrumentation,adaptive,optics,simulation,simulator,telescope,spectrometer
Platform: any
